BingPython.py
bingpython-0.0.21.dist-info/LICENSE
bingpython-0.0.21.dist-info/METADATA
bingpython-0.0.21.dist-info/WHEEL
bingpython-0.0.21.dist-info/top_level.txt
bingpython-0.0.21.dist-info/RECORD
