Metadata-Version: 2.1
Name: bingpython
Version: 0.0.21
Summary: Bing AI Chat API
Home-page: https://github.com/alicangnll/BingGPT-Python
Author: Ali Can Gönüllü
Author-email: alicangonullu@yahoo.com
License: GNU General Public License v2.0
Project-URL: Bug Report, https://github.com/alicangnll/BingGPT-Python/issues/new
Classifier: License :: OSI Approved :: GNU General Public License v2 (GPLv2)
Classifier: Intended Audience :: Developers
Classifier: Topic :: Software Development :: Libraries :: Python Modules
Classifier: Programming Language :: Python :: 3.8
Classifier: Programming Language :: Python :: 3.9
Classifier: Programming Language :: Python :: 3.10
Classifier: Programming Language :: Python :: 3.11
License-File: LICENSE
Requires-Dist: asyncio
Requires-Dist: requests
Requires-Dist: websockets
Requires-Dist: rich
Requires-Dist: certifi
Requires-Dist: uuid
